meupacote_renato/__init__.py
meupacote_renato/modulo.py
meupacote_renato-0.1.0.dist-info/METADATA
meupacote_renato-0.1.0.dist-info/WHEEL
meupacote_renato-0.1.0.dist-info/top_level.txt
meupacote_renato-0.1.0.dist-info/RECORD
