Metadata-Version: 2.1
Name: meupacote_renato
Version: 0.1.0
Summary: Uma descrição do seu pacote
Home-page: https://github.com/seuusuario/meupacote
Author: renato_snp
Author-email: renatoguitarblues@gmail.com
Classifier: Programming Language :: Python :: 3
Classifier: License :: OSI Approved :: MIT License
Classifier: Operating System :: OS Independent
Requires-Python: >=3.6
Requires-Dist: requests
Requires-Dist: numpy
Requires-Dist: pandas
Requires-Dist: scikit-learn
